README.rst
setup.cfg
setup.py
django_filepicker_model/__init__.py
django_filepicker_model/manage.py
django_filepicker_model/models.py
django_filepicker_model/settings.py
django_filepicker_model/utils.py
django_filepicker_model.egg-info/PKG-INFO
django_filepicker_model.egg-info/SOURCES.txt
django_filepicker_model.egg-info/dependency_links.txt
django_filepicker_model.egg-info/not-zip-safe
django_filepicker_model.egg-info/requires.txt
django_filepicker_model.egg-info/top_level.txt
django_filepicker_model/migrations/0001_initial.py
django_filepicker_model/migrations/__init__.py