Metadata-Version: 1.0
Name: django-filepicker-model
Version: 0.1.2
Summary: Filepicker for Django without a frontend
Home-page: http://github.com/sevenleague/django-filepicker-model
Author: jpwagner
Author-email: jim@sevenleague.co
License: UNKNOWN
Platform: UNKNOWN
